betterdicts/VERSION.py
betterdicts/__init__.py
betterdicts/betterdict.py
betterdicts/codeio.py
betterdicts/dynamic_dict.py
betterdicts/jsdict.py
betterdicts/number_dict.py
betterdicts/persistent.py
betterdicts/stack_dict.py
betterdicts-0.5.0.dist-info/LICENSE.txt
betterdicts-0.5.0.dist-info/METADATA
betterdicts-0.5.0.dist-info/WHEEL
betterdicts-0.5.0.dist-info/RECORD
