Metadata-Version: 2.1
Name: betterdicts
Version: 0.5.0
Summary: Better dictionary types.
Home-page: https://gitlab.com/franksh/betterdicts
License: Apache-2.0
Keywords: dict,prelude,utility,convenience,ergonomics,persistent,stack,attributes
Author: Frank S. Hestvik
Author-email: tristesse@gmail.com
Requires-Python: >=3.8,<4.0
Classifier: Development Status :: 4 - Beta
Classifier: License :: OSI Approved :: Apache Software License
Classifier: Programming Language :: Python :: 3
Classifier: Programming Language :: Python :: 3.8
Classifier: Programming Language :: Python :: 3.9
Classifier: Programming Language :: Python :: 3.10
Classifier: Programming Language :: Python :: 3.11
Classifier: Topic :: Utilities
Project-URL: Repository, https://gitlab.com/franksh/betterdicts
